TorchJotter/__init__.py
TorchJotter/__main__.py
TorchJotter/fastcmd/__init__.py
TorchJotter/fastcmd/init_cmd.py
TorchJotter/fastcmd/list_cmd.py
TorchJotter/fastcmd/log_cmd.py
TorchJotter/fastcmd/revert_cmd.py
TorchJotter/fastgit/__init__.py
TorchJotter/fastgit/committer.py
TorchJotter/fastgit/normal/.fitconfig
TorchJotter/fastgit/normal/.gitignore
TorchJotter/fastgit/normal/main
TorchJotter/fastgit/normal/logs/default.cfg
TorchJotter/fastlog/__init__.py
TorchJotter/fastlog/log_read.py
TorchJotter/fastlog/logger.py
TorchJotter/fastlog/utils.py
TorchJotter/fastserver/__init__.py
TorchJotter/fastserver/app.py
TorchJotter/fastserver/chart_app.py
TorchJotter/fastserver/folder_app.py
TorchJotter/fastserver/line_app.py
TorchJotter/fastserver/multi_char_app.py
TorchJotter/fastserver/summary_app.py
TorchJotter/fastserver/table_app.py
TorchJotter/fastserver/server/__init__.py
TorchJotter/fastserver/server/app_utils.py
TorchJotter/fastserver/server/chart_utils.py
TorchJotter/fastserver/server/data_container.py
TorchJotter/fastserver/server/folder_utils.py
TorchJotter/fastserver/server/log_config_parser.py
TorchJotter/fastserver/server/server_config.py
TorchJotter/fastserver/server/summary_utils.py
TorchJotter/fastserver/server/table_utils.py
TorchJotter/fastserver/server/utils.py
TorchJotter/fastserver/static/css/bootstrap-editable.css
TorchJotter/fastserver/static/css/bootstrap-slider.css
TorchJotter/fastserver/static/css/bootstrap-table-filter-control.css
TorchJotter/fastserver/static/css/bootstrap-table-reorder-rows.css
TorchJotter/fastserver/static/css/bootstrap-table.css
TorchJotter/fastserver/static/css/bootstrap-table.min.css
TorchJotter/fastserver/static/css/bootstrap-theme.css
TorchJotter/fastserver/static/css/bootstrap-theme.css.map
TorchJotter/fastserver/static/css/bootstrap-theme.min.css
TorchJotter/fastserver/static/css/bootstrap-theme.min.css.map
TorchJotter/fastserver/static/css/bootstrap.css
TorchJotter/fastserver/static/css/bootstrap.css.map
TorchJotter-0.9.14.dist-info/LICENSE
TorchJotter-0.9.14.dist-info/METADATA
TorchJotter-0.9.14.dist-info/WHEEL
TorchJotter-0.9.14.dist-info/entry_points.txt
TorchJotter-0.9.14.dist-info/top_level.txt
TorchJotter-0.9.14.dist-info/RECORD
