Metadata-Version: 2.1
Name: TorchJotter
Version: 0.9.14
Summary: TorchJotter: Log tool for Deep Learning, developed by Fudan FastNLP Team
License: Apache license
Platform: UNKNOWN
Requires-Python: >=3.7
License-File: LICENSE
Requires-Dist: docopt (>=0.6.2)
Requires-Dist: flask (>=1.0.2)
Requires-Dist: numpy (>=1.16.4)
Requires-Dist: gitpython (>=3.1.2)
